mynutrition/__init__.py
mynutrition/core.py
mynutrition-0.1.dist-info/METADATA
mynutrition-0.1.dist-info/WHEEL
mynutrition-0.1.dist-info/top_level.txt
mynutrition-0.1.dist-info/RECORD
