Metadata-Version: 2.4
Name: mynutrition
Version: 0.1
Summary: Nutrition tools and API integration for dietary analysis
Home-page: https://github.com/yourusername/mynutrition
Author: Your Name
Author-email: your.email@example.com
Classifier: Programming Language :: Python :: 3
Classifier: License :: OSI Approved :: MIT License
Requires-Dist: streamlit
Requires-Dist: requests
Requires-Dist: pandas
Requires-Dist: numpy
Requires-Dist: matplotlib
Dynamic: author
Dynamic: author-email
Dynamic: classifier
Dynamic: home-page
Dynamic: requires-dist
Dynamic: summary
